seareport_data/__init__.py
seareport_data/_copernicus.py
seareport_data/_core.py
seareport_data/_emodnet.py
seareport_data/_enforce_literals.py
seareport_data/_etopo.py
seareport_data/_etopo1.py
seareport_data/_gebco.py
seareport_data/_gshhg.py
seareport_data/_osm.py
seareport_data/_rtopo.py
seareport_data/_srtm15p.py
seareport_data/_utm.py
seareport_data/py.typed
seareport_data/registry.json
seareport_data-0.3.2.dist-info/METADATA
seareport_data-0.3.2.dist-info/WHEEL
seareport_data-0.3.2.dist-info/licenses/LICENSE
seareport_data-0.3.2.dist-info/RECORD
