Metadata-Version: 2.4
Name: seareport-data
Version: 0.3.2
Summary: 
License-File: LICENSE
Author: Panos Mavrogiorgos
Author-email: pmav99@gmail.com
Requires-Python: >=3.10
Classifier: Programming Language :: Python :: 3
Classifier: Programming Language :: Python :: 3.10
Classifier: Programming Language :: Python :: 3.11
Classifier: Programming Language :: Python :: 3.12
Classifier: Programming Language :: Python :: 3.13
Classifier: Programming Language :: Python :: 3.14
Requires-Dist: copernicusmarine
Requires-Dist: dask[complete]
Requires-Dist: geopandas
Requires-Dist: httpx
Requires-Dist: platformdirs
Requires-Dist: shapely
Requires-Dist: stamina
Requires-Dist: tqdm
Requires-Dist: xarray[accel,io]
Requires-Dist: xxhash
Requires-Dist: zstandard
